google_nest_client/__init__.py
google_nest_client/api_client.py
google_nest_client/caching_client.py
google_nest_client/camera.py
google_nest_client/client.py
google_nest_client/device.py
google_nest_client/device_cache.py
google_nest_client/thermostat.py
google_nest_client-1.1.0.dist-info/LICENSE
google_nest_client-1.1.0.dist-info/METADATA
google_nest_client-1.1.0.dist-info/WHEEL
google_nest_client-1.1.0.dist-info/top_level.txt
google_nest_client-1.1.0.dist-info/RECORD
