Metadata-Version: 2.1
Name: google-nest-client
Version: 1.1.0
Summary: Google Nest API Client
Home-page: UNKNOWN
Author: Jimming Cheng
Author-email: jimming@gmail.com
License: UNKNOWN
Platform: UNKNOWN
Classifier: Programming Language :: Python :: 3
Classifier: License :: OSI Approved :: MIT License
Classifier: Operating System :: OS Independent
License-File: LICENSE
Requires-Dist: opencv-python
Requires-Dist: requests
